mothpriest/__init__.py
mothpriest-1.0.0.dist-info/METADATA
mothpriest-1.0.0.dist-info/WHEEL
mothpriest-1.0.0.dist-info/top_level.txt
mothpriest-1.0.0.dist-info/RECORD
